setup.py
ipystata/Example.py
ipystata/__init__.py
ipystata/config.py
ipystata/ipystata_magic.py
ipystata/ipystata_magic_batch.py
ipystata.egg-info/PKG-INFO
ipystata.egg-info/SOURCES.txt
ipystata.egg-info/dependency_links.txt
ipystata.egg-info/not-zip-safe
ipystata.egg-info/top_level.txt