Metadata-Version: 1.0
Name: ipystata
Version: 0.3.6
Summary: Enables the use of Stata together with Python via Jupyter (IPython) notebooks.
Home-page: https://github.com/TiesdeKok/ipystata
Author: TiesdeKok
Author-email: t.c.j.dekok@tilburguniversity.edu
License: MIT
Platform: UNKNOWN
